turta_modular/Turta_ALS_Gesture_Module.py
turta_modular/Turta_Accel_Tilt_Module.py
turta_modular/Turta_Buzzer_Button_Module.py
turta_modular/Turta_Environmental_Module.py
turta_modular/Turta_IRRemote_Module.py
turta_modular/Turta_PIR_Motion_Module.py
turta_modular/Turta_Photocoupler_Module.py
turta_modular/Turta_SS_Relay_Module.py
turta_modular/__init__.py
turta_modular-1.0.0.dist-info/LICENSE
turta_modular-1.0.0.dist-info/METADATA
turta_modular-1.0.0.dist-info/WHEEL
turta_modular-1.0.0.dist-info/top_level.txt
turta_modular-1.0.0.dist-info/RECORD
