Metadata-Version: 2.1
Name: turta-modular
Version: 1.0.0
Summary: Python Libraries for Turta Modular System
Home-page: https://www.turta.io/modular
Author: Turta LLC
Author-email: hello@turta.io
License: UNKNOWN
Project-URL: Documentation, https://docs.turta.io
Project-URL: Community, https://community.turta.io
Project-URL: GitHub Repository, https://github.com/Turta-io/Modular
Platform: UNKNOWN
Classifier: Development Status :: 5 - Production/Stable
Classifier: Intended Audience :: Developers
Classifier: Programming Language :: Python
Classifier: License :: OSI Approved :: MIT License
Classifier: Operating System :: Unix
Classifier: Topic :: System :: Hardware
Requires-Dist: RPi.GPIO
Requires-Dist: smbus
Requires-Dist: spidev
